cranelift/__init__.py
cranelift/__init__.pyi
cranelift/cranelift.cp311-win_amd64.pyd
cranelift/py.typed
cranelift_py-0.1.0.dist-info/METADATA
cranelift_py-0.1.0.dist-info/WHEEL
cranelift_py-0.1.0.dist-info/RECORD
