Metadata-Version: 2.4
Name: cranelift-py
Version: 0.1.0
Classifier: Programming Language :: Rust
Classifier: Programming Language :: Python :: Implementation :: CPython
Classifier: Programming Language :: Python :: Implementation :: PyPy
Classifier: Topic :: Software Development :: Compilers
Summary: Cranelift Python bindings
License: MIT
Requires-Python: >=3.8
